Workbook

Sheet READ ME
A1: GHMD Territory Affordability Model — Public-Source Methodology
A3: PURPOSE: Screen geographies for financed-purchase affordability of a high-ticket package, using only publicly available, citable data.
A5: DATA SOURCES (all public):
A6: 1. Consumer APR range 0%-24.99%, 3-60 months, $300-$25,000: U.S. Bank Avvance public FAQ — avvance.usbank.com/index.html (accessed Jul 2026)
A7: 2. Average FICO Score by state (Sept 2025): Experian, 'What Is the Average Credit Score in the US?' (pub. Mar 30, 2026) — experian.com/blogs/ask-experian/what-is-the-average-credit-score-in-the-u-s/
A8: 3. National FICO distribution by range (2025): same Experian report — Poor(300-579) 14.7%, Fair(580-669) 14.9%, Good(670-739) 20.1%, Very Good(740-799) 27.5%, Exceptional(800-850) 22.8%
A9: 4. Median household income by state (2024): U.S. Census Bureau via FRED release table 'Real Median Household Income by State' — fred.stlouisfed.org/release/tables?eid=259515&rid=249
A10: 5. Local income distribution (Territory Calculator tab): U.S. Census ACS table B19001, data.census.gov — pull for any county/CBSA/zip
A11: 6. Subprime APR benchmarks: NerdWallet avg ~26.65% for <630 scores (Jun 2026); Bankrate personal loan rates 8%-36%
A12: 7. Promotional (0% APR) merchant fee benchmarks: publicly documented dealer fees ~8-25% (GreenSky 0-26.6%, Service Finance 1.25-24%, Synchrony 4.5-9%, EnerBank ~6% for 12-18mo same-as-cash)
A14: HOW TO USE:
A15: - Assumptions tab: set package price, APR, term, payment-to-income threshold, FICO cutoff. Blue cells are inputs.
... A29: 10. GreenSky Form 10-K FY2019 (SEC EDGAR) — merchants pay upfront transaction fees; 'the transaction fee rate depends on the terms of financing underlying the consumer loans' — sec.gov/Archives/edgar/data/0001712923/000171292320000010/gsky-20191231.htm

Sheet Assumptions
A1: Model Assumptions
A3: Standard financing scenario
A4: Package price ($) | B4: 8500 | C4: GHMD highest package
A5: APR — conservative (max of public range) | B5: 0.2499 | C5: Source: U.S. Bank Avvance public FAQ, avvance.usbank.com, accessed Jul 2026 (range 0%-24.99%)
A6: Term (months) | B6: 60 | C6: Public Avvance range: 3-60 months
A7: Payment-to-income (PTI) threshold | B7: 0.08 | C7: Modeling assumption: 8% of gross monthly HH income for a discretionary installment payment; consistent with keeping total obligations within the widely used 36% back-end DTI convention
A8: Minimum FICO cutoff (credit screen) | B8: 670 | C8: 670 = bottom of "Good" range (Experian/FICO ranges)
A10: Promotional (0% APR) scenario
A11: Promo term (months) | B11: 36 | C11: Longest common 0% plan cited (12/24/36)
A12: Merchant promo fee (% of ticket) | B12: 0.15 | C12: Input estimate; public benchmarks ~8-25% for promo/same-as-cash plans
A14: Calculated
A15: Monthly payment — standard APR | B15: =B4*(B5/12)/(1-(1+B5/12)^-B6) -> 249.43642
A16: Required annual HH income — standard | B16: =B15*12/B7 -> 37415.463
A17: Monthly payment — 0% promo | B17: =B4/B11 -> 236.11111
A18: Required annual HH income — promo | B18: =B17*12/B7 -> 35416.667
A19: Franchisee net receipt under promo | B19: =B4*(1-B12) -> 7225
A20: Franchisee margin give-up per promo sale | B20: =B4*B12 -> 1275
A22: National FICO distribution (Experian, Sept 2025)
A23: Range | B23: Share
A24: Poor (300-579) | B24: 0.147
A25: Fair (580-669) | B25: 0.149
A26: Good (670-739) | B26: 0.201
A27: Very Good (740-799) | B27: 0.275
A28: Exceptional (800-850) | B28: 0.228
A29: Share at/above 670 (credit-eligible, national) | B29: =SUM(B26:B28) -> 0.704 | C29: Used as default credit screen in Territory Calculator; adjust locally using avg-FICO differential
A31: Sensitivity — required annual HH income (standard scenario)
A32: PTI threshold | B32: Required income
A33: 0.05 | B33: =$B$15*12/A33 -> 59864.74
A34: 0.08 | B34: =$B$15*12/A34 -> 37415.463
A35: 0.1 | B35: =$B$15*12/A35 -> 29932.37
A36: PTI is a stated modeling convention (see methodology memo, Limitations). Run all three; disclose which one is used.

Sheet State Screening
A1: State | B1: Abbr | C1: Avg FICO (Sept 2025) | D1: Median HH Income (2024, $) | E1: Income Affordability Multiple | F1: FICO vs National Avg (713) | G1: Income Percentile | H1: Credit Percentile | I1: Composite Territory Score (0-100) | J1: Est. Share FICO ≥670 (derived)
A2: Alabama | B2: AL | C2: 689 | D2: 65560 | E2: =D2/Assumptions!$B$16 -> 1.7522167 | F2: =C2-713 -> -24 | G2: =PERCENTRANK($D$2:$D$52,D2) -> 0.14 | H2: =PERCENTRANK($C$2:$C$52,C2) -> 0.04 | I2: =ROUND(50*(G2+H2),0) -> 9 | J2: =IF((1383-C2)<=300,1,IF((1383-C2)<580,0.853+0.147*(580-(1383-C2))/280,IF((1383-C2)<670,0.704+0.149*(670-(1383-C2))/90,IF((1383-C2)<740,0.503+0.201*(740-(1383-C2))/70,IF((1383-C2)<800,0.228+0.275*(800-(1383-C2))/60,0.228*(850-(1383-C2))/50))))) -> 0.63508571
A3: Alaska | B3: AK | C3: 720 | D3: 91260 | E3: =D3/Assumptions!$B$16 -> 2.4390985 | F3: =C3-713 -> 7 | G3: =PERCENTRANK($D$2:$D$52,D3) -> 0.72 | H3: =PERCENTRANK($C$2:$C$52,C3) -> 0.5 | I3: =ROUND(50*(G3+H3),0) -> 61 | J3: =IF((1383-C3)<=300,1,IF((1383-C3)<580,0.853+0.147*(580-(1383-C3))/280,IF((1383-C3)<670,0.704+0.149*(670-(1383-C3))/90,IF((1383-C3)<740,0.503+0.201*(740-(1383-C3))/70,IF((1383-C3)<800,0.228+0.275*(800-(1383-C3))/60,0.228*(850-(1383-C3))/50))))) -> 0.71558889
A4: Arizona | B4: AZ | C4: 709 | D4: 84700 | E4: =D4/Assumptions!$B$16 -> 2.2637699 | F4: =C4-713 -> -4 | G4: =PERCENTRANK($D$2:$D$52,D4) -> 0.52 | H4: =PERCENTRANK($C$2:$C$52,C4) -> 0.3 | I4: =ROUND(50*(G4+H4),0) -> 41 | J4: =IF((1383-C4)<=300,1,IF((1383-C4)<580,0.853+0.147*(580-(1383-C4))/280,IF((1383-C4)<670,0.704+0.149*(670-(1383-C4))/90,IF((1383-C4)<740,0.503+0.201*(740-(1383-C4))/70,IF((1383-C4)<800,0.228+0.275*(800-(1383-C4))/60,0.228*(850-(1383-C4))/50))))) -> 0.69251429
A5: Arkansas | B5: AR | C5: 693 | D5: 64840 | E5: =D5/Assumptions!$B$16 -> 1.7329734 | F5: =C5-713 -> -20 | G5: =PERCENTRANK($D$2:$D$52,D5) -> 0.1 | H5: =PERCENTRANK($C$2:$C$52,C5) -> 0.1 | I5: =ROUND(50*(G5+H5),0) -> 10 | J5: =IF((1383-C5)<=300,1,IF((1383-C5)<580,0.853+0.147*(580-(1383-C5))/280,IF((1383-C5)<670,0.704+0.149*(670-(1383-C5))/90,IF((1383-C5)<740,0.503+0.201*(740-(1383-C5))/70,IF((1383-C5)<800,0.228+0.275*(800-(1383-C5))/60,0.228*(850-(1383-C5))/50))))) -> 0.64657143
A6: California | B6: CA | C6: 721 | D6: 100600 | E6: =D6/Assumptions!$B$16 -> 2.6887279 | F6: =C6-713 -> 8 | G6: =PERCENTRANK($D$2:$D$52,D6) -> 0.86 | H6: =PERCENTRANK($C$2:$C$52,C6) -> 0.58 | I6: =ROUND(50*(G6+H6),0) -> 72 | J6: =IF((1383-C6)<=300,1,IF((1383-C6)<580,0.853+0.147*(580-(1383-C6))/280,IF((1383-C6)<670,0.704+0.149*(670-(1383-C6))/90,IF((1383-C6)<740,0.503+0.201*(740-(1383-C6))/70,IF((1383-C6)<800,0.228+0.275*(800-(1383-C6))/60,0.228*(850-(1383-C6))/50))))) -> 0.71724444
A7: Colorado | B7: CO | C7: 729 | D7: 106500 | E7: =D7/Assumptions!$B$16 -> 2.8464167 | F7: =C7-713 -> 16 | G7: =PERCENTRANK($D$2:$D$52,D7) -> 0.94 | H7: =PERCENTRANK($C$2:$C$52,C7) -> 0.74 | I7: =ROUND(50*(G7+H7),0) -> 84 | J7: =IF((1383-C7)<=300,1,IF((1383-C7)<580,0.853+0.147*(580-(1383-C7))/280,IF((1383-C7)<670,0.704+0.149*(670-(1383-C7))/90,IF((1383-C7)<740,0.503+0.201*(740-(1383-C7))/70,IF((1383-C7)<800,0.228+0.275*(800-(1383-C7))/60,0.228*(850-(1383-C7))/50))))) -> 0.73048889
A8: Connecticut | B8: CT | C8: 724 | D8: 99240 | E8: =D8/Assumptions!$B$16 -> 2.6523793 | F8: =C8-713 -> 11 | G8: =PERCENTRANK($D$2:$D$52,D8) -> 0.84 | H8: =PERCENTRANK($C$2:$C$52,C8) -> 0.66 | I8: =ROUND(50*(G8+H8),0) -> 75 | J8: =IF((1383-C8)<=300,1,IF((1383-C8)<580,0.853+0.147*(580-(1383-C8))/280,IF((1383-C8)<670,0.704+0.149*(670-(1383-C8))/90,IF((1383-C8)<740,0.503+0.201*(740-(1383-C8))/70,IF((1383-C8)<800,0.228+0.275*(800-(1383-C8))/60,0.228*(850-(1383-C8))/50))))) -> 0.72221111
A9: Delaware | B9: DE | C9: 713 | D9: 85860 | E9: =D9/Assumptions!$B$16 -> 2.2947732 | F9: =C9-713 -> 0 | G9: =PERCENTRANK($D$2:$D$52,D9) -> 0.58 | H9: =PERCENTRANK($C$2:$C$52,C9) -> 0.38 | I9: =ROUND(50*(G9+H9),0) -> 48 | J9: =IF((1383-C9)<=300,1,IF((1383-C9)<580,0.853+0.147*(580-(1383-C9))/280,IF((1383-C9)<670,0.704+0.149*(670-(1383-C9))/90,IF((1383-C9)<740,0.503+0.201*(740-(1383-C9))/70,IF((1383-C9)<800,0.228+0.275*(800-(1383-C9))/60,0.228*(850-(1383-C9))/50))))) -> 0.704
A10: District of Columbia | B10: DC | C10: 711 | D10: 104800 | E10: =D10/Assumptions!$B$16 -> 2.800981 | F10: =C10-713 -> -2 | G10: =PERCENTRANK($D$2:$D$52,D10) -> 0.92 | H10: =PERCENTRANK($C$2:$C$52,C10) -> 0.34 | I10: =ROUND(50*(G10+H10),0) -> 63 | J10: =IF((1383-C10)<=300,1,IF((1383-C10)<580,0.853+0.147*(580-(1383-C10))/280,IF((1383-C10)<670,0.704+0.149*(670-(1383-C10))/90,IF((1383-C10)<740,0.503+0.201*(740-(1383-C10))/70,IF((1383-C10)<800,0.228+0.275*(800-(1383-C10))/60,0.228*(850-(1383-C10))/50))))) -> 0.69825714
A11: Florida | B11: FL | C11: 704 | D11: 75630 | E11: =D11/Assumptions!$B$16 -> 2.0213568 | F11: =C11-713 -> -9 | G11: =PERCENTRANK($D$2:$D$52,D11) -> 0.18 | H11: =PERCENTRANK($C$2:$C$52,C11) -> 0.24 | I11: =ROUND(50*(G11+H11),0) -> 21 | J11: =IF((1383-C11)<=300,1,IF((1383-C11)<580,0.853+0.147*(580-(1383-C11))/280,IF((1383-C11)<670,0.704+0.149*(670-(1383-C11))/90,IF((1383-C11)<740,0.503+0.201*(740-(1383-C11))/70,IF((1383-C11)<800,0.228+0.275*(800-(1383-C11))/60,0.228*(850-(1383-C11))/50))))) -> 0.67815714
A12: Georgia | B12: GA | C12: 692 | D12: 81210 | E12: =D12/Assumptions!$B$16 -> 2.170493 | F12: =C12-713 -> -21 | G12: =PERCENTRANK($D$2:$D$52,D12) -> 0.4 | H12: =PERCENTRANK($C$2:$C$52,C12) -> 0.06 | I12: =ROUND(50*(G12+H12),0) -> 23 | J12: =IF((1383-C12)<=300,1,IF((1383-C12)<580,0.853+0.147*(580-(1383-C12))/280,IF((1383-C12)<670,0.704+0.149*(670-(1383-C12))/90,IF((1383-C12)<740,0.503+0.201*(740-(1383-C12))/70,IF((1383-C12)<800,0.228+0.275*(800-(1383-C12))/60,0.228*(850-(1383-C12))/50))))) -> 0.6437
A13: Hawaii | B13: HI | C13: 730 | D13: 98240 | E13: =D13/Assumptions!$B$16 -> 2.6256524 | F13: =C13-713 -> 17 | G13: =PERCENTRANK($D$2:$D$52,D13) -> 0.82 | H13: =PERCENTRANK($C$2:$C$52,C13) -> 0.78 | I13: =ROUND(50*(G13+H13),0) -> 80 | J13: =IF((1383-C13)<=300,1,IF((1383-C13)<580,0.853+0.147*(580-(1383-C13))/280,IF((1383-C13)<670,0.704+0.149*(670-(1383-C13))/90,IF((1383-C13)<740,0.503+0.201*(740-(1383-C13))/70,IF((1383-C13)<800,0.228+0.275*(800-(1383-C13))/60,0.228*(850-(1383-C13))/50))))) -> 0.73214444
... A52: Wyoming | B52: WY | C52: 722 | D52: 78680 | E52: =D52/Assumptions!$B$16 -> 2.1028739 | F52: =C52-713 -> 9 | G52: =PERCENTRANK($D$2:$D$52,D52) -> 0.28 | H52: =PERCENTRANK($C$2:$C$52,C52) -> 0.62 | I52: =ROUND(50*(G52+H52),0) -> 45 | J52: =IF((1383-C52)<=300,1,IF((1383-C52)<580,0.853+0.147*(580-(1383-C52))/280,IF((1383-C52)<670,0.704+0.149*(670-(1383-C52))/90,IF((1383-C52)<740,0.503+0.201*(740-(1383-C52))/70,IF((1383-C52)<800,0.228+0.275*(800-(1383-C52))/60,0.228*(850-(1383-C52))/50))))) -> 0.7189
A54: Sources: Avg FICO — Experian (Sept 2025 data, pub. Mar 2026). Median HH income — U.S. Census Bureau via FRED (2024). Income Affordability Multiple = median income ÷ required income from Assumptions. Composite = average of income & credit percentile ranks × 100. Screening/ranking tool only — size specific territories on the Territory Calculator tab.
A55: Column J derivation (labeled ESTIMATE): national FICO band distribution (Experian, Sept 2025) shifted by each state’s average-score differential vs the 713 national average, interpolated uniformly within bands. Two verified public inputs, one transparent approximation — reproducible from columns C + the Assumptions band table. Sanity check: a state at exactly 713 returns 70.4%, the national share ≥670. Use this instead of the flat national 70.4% in the Territory Calculator for state-sensitive sizing.

Sheet Territory Calculator
A1: Territory Calculator — size a specific protected territory
A2: Enter local data from data.census.gov (ACS table B19001) for the candidate geography (county / CBSA / zip set).
A4: Step 1 — Local inputs
A5: Geography name | B5: Example County
A6: Total households (ACS B19001 line 1) | B6: 100000 | E6: From data.census.gov
A7: Credit-eligible share (default: national ≥670) | B7: =Assumptions!B29 -> 0.704 | E7: Defaults to Assumptions!B29; override with local estimate if avg state FICO differs materially
A8: Expected market penetration of addressable HH | B8: 0.01 | E8: Franchisor assumption — document basis
A9: Annual customers needed per location (breakeven+) | B9: 400 | E9: From GHMD unit economics
A11: Step 2 — Paste ACS B19001 household counts by income bracket
A12: Bracket | B12: Households (paste) | C12: Lower | D12: Upper | E12: Households above required income (calc)
A13: < $10,000 | B13: 2000 | C13: 0 | D13: 10000 | E13: =IF(Assumptions!$B$16<=C13,B13,IF(Assumptions!$B$16>=D13,0,(D13-Assumptions!$B$16)/(D13-C13)*B13)) -> 0
A14: $10,000-14,999 | B14: 1500 | C14: 10000 | D14: 15000 | E14: =IF(Assumptions!$B$16<=C14,B14,IF(Assumptions!$B$16>=D14,0,(D14-Assumptions!$B$16)/(D14-C14)*B14)) -> 0
A15: $15,000-19,999 | B15: 1800 | C15: 15000 | D15: 20000 | E15: =IF(Assumptions!$B$16<=C15,B15,IF(Assumptions!$B$16>=D15,0,(D15-Assumptions!$B$16)/(D15-C15)*B15)) -> 0
A16: $20,000-24,999 | B16: 2000 | C16: 20000 | D16: 25000 | E16: =IF(Assumptions!$B$16<=C16,B16,IF(Assumptions!$B$16>=D16,0,(D16-Assumptions!$B$16)/(D16-C16)*B16)) -> 0
A17: $25,000-29,999 | B17: 2200 | C17: 25000 | D17: 30000 | E17: =IF(Assumptions!$B$16<=C17,B17,IF(Assumptions!$B$16>=D17,0,(D17-Assumptions!$B$16)/(D17-C17)*B17)) -> 0
A18: $30,000-34,999 | B18: 2400 | C18: 30000 | D18: 35000 | E18: =IF(Assumptions!$B$16<=C18,B18,IF(Assumptions!$B$16>=D18,0,(D18-Assumptions!$B$16)/(D18-C18)*B18)) -> 0
A19: $35,000-39,999 | B19: 2500 | C19: 35000 | D19: 40000 | E19: =IF(Assumptions!$B$16<=C19,B19,IF(Assumptions!$B$16>=D19,0,(D19-Assumptions!$B$16)/(D19-C19)*B19)) -> 1292.2686
A20: $40,000-44,999 | B20: 2600 | C20: 40000 | D20: 45000 | E20: =IF(Assumptions!$B$16<=C20,B20,IF(Assumptions!$B$16>=D20,0,(D20-Assumptions!$B$16)/(D20-C20)*B20)) -> 2600
A21: $45,000-49,999 | B21: 2700 | C21: 45000 | D21: 50000 | E21: =IF(Assumptions!$B$16<=C21,B21,IF(Assumptions!$B$16>=D21,0,(D21-Assumptions!$B$16)/(D21-C21)*B21)) -> 2700
A22: $50,000-59,999 | B22: 5600 | C22: 50000 | D22: 60000 | E22: =IF(Assumptions!$B$16<=C22,B22,IF(Assumptions!$B$16>=D22,0,(D22-Assumptions!$B$16)/(D22-C22)*B22)) -> 5600
A23: $60,000-74,999 | B23: 8200 | C23: 60000 | D23: 75000 | E23: =IF(Assumptions!$B$16<=C23,B23,IF(Assumptions!$B$16>=D23,0,(D23-Assumptions!$B$16)/(D23-C23)*B23)) -> 8200
A24: $75,000-99,999 | B24: 14500 | C24: 75000 | D24: 100000 | E24: =IF(Assumptions!$B$16<=C24,B24,IF(Assumptions!$B$16>=D24,0,(D24-Assumptions!$B$16)/(D24-C24)*B24)) -> 14500
... A28: $200,000+ | B28: 13000 | C28: 200000 | D28: 10000000 | E28: =IF(Assumptions!$B$16<=C28,B28,IF(Assumptions!$B$16>=D28,0,(D28-Assumptions!$B$16)/(D28-C28)*B28)) -> 13000
A30: Step 3 — Results
A31: Required annual HH income (from Assumptions) | B31: =Assumptions!B16 -> 37415.463
A32: Total households pasted | B32: =SUM(B13:B28) -> 100000 | E32: Should reconcile to B6
A33: Households above required income | B33: =SUM(E13:E28) -> 86892.269 | E33: Linear interpolation within containing bracket
A34: % of households income-qualified | B34: =B33/B32 -> 0.86892269
A35: Addressable households (income × credit screen) | B35: =B33*B7 -> 61172.157
A36: Expected annual customers in geography | B36: =B35*B8 -> 611.72157
A37: Supportable locations (territory sizing) | B37: =B36/B9 -> 1.5293039 | E37: If < 1.0, expand the geography until ≥ 1.0 — that boundary is the protected territory
A39: Note: top bracket ($200,000+) uses a $10M synthetic upper bound; if required income lands in this bracket, interpolation understates precision — use a finer-grained ACS table (B19001 at tract level) instead.

Sheet Lender Tier Scenarios
A1: Lender Tier Scenarios — what each financing tier does to affordability
A2: Generic tiers; plug in any lender’s published terms. Key finding: APR and TERM move required income far more than credit cutoffs move population share.
A4: Tier (generic) | B4: Amount financed ($) | C4: APR | D4: Term (mo) | E4: Monthly payment | F4: Req. income @8% PTI | G4: Req. income @5% PTI | H4: Notes
A5: Prime bank installment — public max APR | B5: 8500 | C5: 0.2499 | D5: 60 | E5: =IF(C5=0,B5/D5,B5*(C5/12)/(1-(1+C5/12)^-D5)) -> 249.43642 | F5: =E5*12/0.08 -> 37415.463 | G5: =E5*12/0.05 -> 59864.74 | H5: Public anchor: U.S. Bank Avvance FAQ, 0%–24.99%, 3–60 mo. BASE CASE.
A6: 0% promotional, 36 mo | B6: 8500 | C6: 0 | D6: 36 | E6: =IF(C6=0,B6/D6,B6*(C6/12)/(1-(1+C6/12)^-D6)) -> 236.11111 | F6: =E6*12/0.08 -> 35416.667 | G6: =E6*12/0.05 -> 56666.667 | H6: Merchant absorbs promo fee (~8–25%+ of ticket; fee rate depends on financing terms — GreenSky 10-K, SEC). Model revenue net of fee.
A7: 0% promotional, 24 mo | B7: 8500 | C7: 0 | D7: 24 | E7: =IF(C7=0,B7/D7,B7*(C7/12)/(1-(1+C7/12)^-D7)) -> 354.16667 | F7: =E7*12/0.08 -> 53125 | G7: =E7*12/0.05 -> 85000 | H7: Shorter promo term → higher payment → smaller affordable pool.
A8: 0% short-term, 12 mo, $7,500 cap | B8: 7500 | C8: 0 | D8: 12 | E8: =IF(C8=0,B8/D8,B8*(C8/12)/(1-(1+C8/12)^-D8)) -> 625 | F8: =E8*12/0.08 -> 93750 | G8: =E8*12/0.05 -> 150000 | H8: Highest monthly payment of any tier despite 0% APR. Also leaves $1,000 cash gap on an $8,500 package. Term dominates APR.
A9: Near-prime marketplace average | B9: 8500 | C9: 0.267 | D9: 48 | E9: =IF(C9=0,B9/D9,B9*(C9/12)/(1-(1+C9/12)^-D9)) -> 289.95468 | F9: =E9*12/0.08 -> 43493.203 | G9: =E9*12/0.05 -> 69589.124 | H9: Public benchmark: NerdWallet avg APR 26.70% for 300–629 scores (Jun 2026).
A10: High-APR subprime, 24 mo | B10: 8500 | C10: 1.2 | D10: 24 | E10: =IF(C10=0,B10/D10,B10*(C10/12)/(1-(1+C10/12)^-D10)) -> 946.0481 | F10: =E10*12/0.08 -> 141907.21 | G10: =E10*12/0.05 -> 227051.54 | H10: Where state law permits (rate caps block this tier in many states — add a state availability flag). ILLUSTRATIVE.
A11: High-APR subprime, 12 mo | B11: 8500 | C11: 1.2 | D11: 12 | E11: =IF(C11=0,B11/D11,B11*(C11/12)/(1-(1+C11/12)^-D11)) -> 1247.4882 | F11: =E11*12/0.08 -> 187123.23 | G11: =E11*12/0.05 -> 299397.16 | H11: Affordability self-defeating at full ticket: required income exceeds the income profile of the credit band it serves.
A13: READING THIS TABLE: wider credit coverage (near-prime/subprime tiers) does NOT proportionally widen the affordable market at full ticket — the payment burden rises faster than the eligible population grows, and the income required at 120% APR exceeds the typical income of subprime borrowers. The defensible base case for territory sizing remains the prime tier at the published maximum APR. Subprime and promo tiers change capture RATE (penetration) more than market SIZE — and penetration must be substantiated from the brand’s own outlet history (NASAA 19.19–19.20).
